tet/__init__.py
tet/_patch_parser.py
tet/agent_session.py
tet/config.py
tet/data_collection.py
tet/finetuning.py
tet/reward.py
tet/schema.py
tet/utils.py
tet/workflow.py
tet/prompts/__init__.py
tet/prompts/system_message.py
nuva-0.1.0.dist-info/METADATA
nuva-0.1.0.dist-info/WHEEL
nuva-0.1.0.dist-info/RECORD
